asa_harmony_mcp/__init__.py
asa_harmony_mcp-0.1.0.dist-info/WHEEL
asa_harmony_mcp-0.1.0.dist-info/entry_points.txt
asa_harmony_mcp-0.1.0.dist-info/METADATA
asa_harmony_mcp-0.1.0.dist-info/RECORD
