Metadata-Version: 2.3
Name: asa-harmony-mcp
Version: 0.1.0
Summary: 鸿蒙开发文档MCP服务
Author: 孤单的城
Author-email: 孤单的城 <10196842+tianlangaa@user.noreply.gitee.com>
Requires-Dist: mcp[cli]>=1.24.0
Requires-Python: >=3.13
